python_boiler_controller/__init__.py
python_boiler_controller/src/__init__.py
python_boiler_controller/src/app/__init__.py
python_boiler_controller/src/app/cli.py
python_boiler_controller/src/app/constants.py
python_boiler_controller/src/models/__init__.py
python_boiler_controller/src/models/boiler.py
python_boiler_controller/src/services/__init__.py
python_boiler_controller/src/services/constants.py
python_boiler_controller/src/services/logger.py
python_boiler_controller/src/services/service_helpers.py
python_boiler_controller/src/services/system_operation.py
python_boiler_controller-0.5.0.dist-info/METADATA
python_boiler_controller-0.5.0.dist-info/WHEEL
python_boiler_controller-0.5.0.dist-info/RECORD
