Metadata-Version: 2.3
Name: python_boiler_controller
Version: 0.5.0
Summary: A sample cli app to control boiler state.
License: MIT
Author: BarathVikraman-Sol-CBE
Author-email: barath.deivasigamani@solitontech.com
Requires-Python: >=3.9
Classifier: License :: OSI Approved :: MIT License
Classifier: Programming Language :: Python :: 3
Classifier: Programming Language :: Python :: 3.9
Classifier: Programming Language :: Python :: 3.10
Classifier: Programming Language :: Python :: 3.11
Classifier: Programming Language :: Python :: 3.12
Classifier: Programming Language :: Python :: 3.13
Requires-Dist: inquirerpy (>=0.3,<0.4)
